promptcreatives/PromptCreatives.py
promptcreatives/__init__.py
promptcreatives-0.0.1.dist-info/METADATA
promptcreatives-0.0.1.dist-info/WHEEL
promptcreatives-0.0.1.dist-info/RECORD
